fuel_efficency_abinbev/__init__.py
fuel_efficency_abinbev/algorithms/__init__.py
fuel_efficency_abinbev/algorithms/a_star.py
fuel_efficency_abinbev/algorithms/context.py
fuel_efficency_abinbev/algorithms/dijkstra.py
fuel_efficency_abinbev/algorithms/path_finding.py
fuel_efficency_abinbev/entities/__init__.py
fuel_efficency_abinbev/entities/down_hill.py
fuel_efficency_abinbev/entities/node.py
fuel_efficency_abinbev/entities/plateau.py
fuel_efficency_abinbev/entities/position.py
fuel_efficency_abinbev/entities/up_hill.py
fuel_efficency_abinbev/entities/valley.py
fuel_efficency_abinbev-0.1.dist-info/METADATA
fuel_efficency_abinbev-0.1.dist-info/WHEEL
fuel_efficency_abinbev-0.1.dist-info/licenses/LICENSE
fuel_efficency_abinbev-0.1.dist-info/RECORD
