Metadata-Version: 2.3
Name: fuel_efficency_abinbev
Version: 0.1
Summary: Fuel Efficency challenge for AB-Inbev
Project-URL: Homepage, https://github.com/sauloleite/fuel-efficency-ab-inbev
Project-URL: Issues, https://github.com/sauloleite/fuel-efficency-ab-inbev/issues
Author-email: Saulo Leite <sjoldeveloper@gmail.com>
License-File: LICENSE
Classifier: License :: OSI Approved :: MIT License
Classifier: Operating System :: OS Independent
Classifier: Programming Language :: Python :: 3
Requires-Python: >=3.10
